LICENSE.txt
MANIFEST.in
README.rst
requirements.txt
setup.cfg
setup.py
pyjob/__init__.py
pyjob/__main__.py
pyjob/cexec.py
pyjob/config.py
pyjob/exception.py
pyjob/factory.py
pyjob/local.py
pyjob/lsf.py
pyjob/misc.py
pyjob/pbs.py
pyjob/pool.py
pyjob/script.py
pyjob/sge.py
pyjob/slurm.py
pyjob/stopwatch.py
pyjob/task.py
pyjob/torque.py
pyjob/version.py
pyjob.egg-info/PKG-INFO
pyjob.egg-info/SOURCES.txt
pyjob.egg-info/dependency_links.txt
pyjob.egg-info/entry_points.txt
pyjob.egg-info/not-zip-safe
pyjob.egg-info/requires.txt
pyjob.egg-info/top_level.txt